analyzrclient/__init__.py
analyzrclient/analyzer.py
analyzrclient/client_basic_auth.py
analyzrclient/client_saml_sso.py
analyzrclient/constants.py
analyzrclient/runner_base.py
analyzrclient/runner_causal.py
analyzrclient/runner_cluster.py
analyzrclient/runner_propensity.py
analyzrclient/runner_regression.py
analyzrclient/runner_task.py
analyzrclient/utils.py
analyzr_sdk_python-1.3.76.dist-info/LICENSE
analyzr_sdk_python-1.3.76.dist-info/METADATA
analyzr_sdk_python-1.3.76.dist-info/WHEEL
analyzr_sdk_python-1.3.76.dist-info/top_level.txt
analyzr_sdk_python-1.3.76.dist-info/RECORD
