Metadata-Version: 2.1
Name: analyzr-sdk-python
Version: 1.3.76
Summary: Python SDK for Analyzr API
Home-page: https://github.com/analyzr-ai/analyzr-sdk-python
Author: Analyzr Team
Author-email: support@analyzr.ai
License: Apache 2.0
Classifier: Programming Language :: Python :: 3
Classifier: Programming Language :: Python :: 3.7
Classifier: Programming Language :: Python :: 3.8
Classifier: Programming Language :: Python :: 3.9
Classifier: Programming Language :: Python :: 3.10
Classifier: Programming Language :: Python :: 3.11
License-File: LICENSE
